vogen/__init__.py
vogen/__main__.py
vogen/pm.py
vogen/config/__init__.py
vogen/synth/__init__.py
vogen/synth/acoustics.py
vogen/synth/f0.py
vogen/synth/g2p.py
vogen/synth/prosody.py
vogen/synth/timetable.py
vogen/synth/utils.py
vogen/synth/models/f0.man.onnx
vogen/synth/models/f0.yue.onnx
vogen/synth/models/g2p.man.onnx
vogen/synth/models/g2p.yue-wz.onnx
vogen/synth/models/g2p.yue.onnx
vogen/synth/models/po.man.onnx
vogen/synth/models/po.yue.onnx
vogen/synth/models/rfft.onnx
vogen-0.0.7.dist-info/LICENSE
vogen-0.0.7.dist-info/METADATA
vogen-0.0.7.dist-info/WHEEL
vogen-0.0.7.dist-info/entry_points.txt
vogen-0.0.7.dist-info/top_level.txt
vogen-0.0.7.dist-info/RECORD
