Metadata-Version: 2.1
Name: vogen
Version: 0.0.7
Summary: An AI based vocal synthesizer implemented in python and onnx, with a music21 interface
Home-page: https://github.com/oxygen-dioxide/vogen
Author: oxygen dioxide
Author-email: 1463567152@qq.com
License: MIT License
Platform: UNKNOWN
Classifier: License :: OSI Approved :: MIT License
Classifier: Programming Language :: Python
Classifier: Programming Language :: Python :: 3
Classifier: Programming Language :: Python :: 3.9
Classifier: Programming Language :: Python :: 3.8
Classifier: Programming Language :: Python :: 3.7
Classifier: Programming Language :: Python :: 3.6
Classifier: Programming Language :: Python :: 3.5
Classifier: Topic :: Multimedia :: Sound/Audio :: MIDI
Classifier: Topic :: Multimedia :: Sound/Audio :: Sound Synthesis
Classifier: Programming Language :: Python :: Implementation :: CPython
Requires-Python: >=3.5.0
License-File: LICENSE
Requires-Dist: wget
Requires-Dist: tqdm
Requires-Dist: numpy
Requires-Dist: pyworld
Requires-Dist: jyutping
Requires-Dist: pypinyin
Requires-Dist: tabulate
Requires-Dist: pyperclip
Requires-Dist: onnxruntime
Requires-Dist: simpleaudio
Requires-Dist: more-itertools
